datasette_permissions_metadata/__init__.py
datasette_permissions_metadata-0.1.dist-info/LICENSE
datasette_permissions_metadata-0.1.dist-info/METADATA
datasette_permissions_metadata-0.1.dist-info/WHEEL
datasette_permissions_metadata-0.1.dist-info/entry_points.txt
datasette_permissions_metadata-0.1.dist-info/top_level.txt
datasette_permissions_metadata-0.1.dist-info/RECORD
