Metadata-Version: 2.1
Name: datasette-permissions-metadata
Version: 0.1
Summary: Configure permissions for Datasette 0.x in metadata.json
Author: Simon Willison
License: Apache-2.0
Project-URL: Homepage, https://github.com/datasette/datasette-permissions-metadata
Project-URL: Changelog, https://github.com/datasette/datasette-permissions-metadata/releases
Project-URL: Issues, https://github.com/datasette/datasette-permissions-metadata/issues
Project-URL: CI, https://github.com/datasette/datasette-permissions-metadata/actions
Classifier: Framework :: Datasette
Classifier: License :: OSI Approved :: Apache Software License
Requires-Python: >=3.8
License-File: LICENSE
Requires-Dist: datasette
Provides-Extra: test
Requires-Dist: pytest ; extra == 'test'
Requires-Dist: pytest-asyncio ; extra == 'test'
